objwrap/__init__.py
objwrap/closure.py
objwrap/core.py
objwrap/wrapper.py
tests/__init__.py
tests/test_closed_wrapper.py
tests/test_wrapper.py
objwrap-0.0.2.dist-info/METADATA
objwrap-0.0.2.dist-info/WHEEL
objwrap-0.0.2.dist-info/top_level.txt
objwrap-0.0.2.dist-info/RECORD
