Metadata-Version: 2.1
Name: objwrap
Version: 0.0.2
Summary: Easy object wrapping in Python.
Home-page: https://github.com/maniospas/objwrap
Author: Emmanouil (Manios) Krasanakis
Author-email: maniospas@hotmail.com
License: UNKNOWN
Platform: UNKNOWN
Classifier: Programming Language :: Python :: 3
Classifier: License :: OSI Approved :: Apache Software License
Classifier: Operating System :: OS Independent
